{
  "header": {
    "tradeId": "BenTest",
    "tradeDate": {
      "date": "01/10/2025",
      "businessDayConvention": "MODFOLLOWING",
      "businessCenters": ["USNY", "CLSA"]
    },
    "effectiveDate": {
      "date": "03/10/2025",
      "businessDayConvention": "MODFOLLOWING",
      "businessCenters": ["USNY", "CLSA"]
    },
    "terminationDate": {
      "date": "03/10/2034",
      "businessDayConvention": "MODFOLLOWING",
      "businessCenters": ["USNY", "CLSA"]
    },
    "party1": {
      "partyId": "ThisBank",
      "partyName": "Banco ABC"
    },
    "party2": {
      "partyId": "OurCounterparty",
      "partyName": "XYZ Corp"
    }
  },
  "legs": [
    {
      "legId": "FIXED-LEG",
      "payerPartyReference": "OurCounterparty",
      "receiverPartyReference": "ThisBank",
      "notionalAmount": 50000000,
      "notionalCurrency": "USD",
      "rateType": "FIXED",
      "fixedRate": 0.0385,
      "paymentFrequency": "6M",
      "dayCountFraction": "30/360",
      "paymentDayConvention": "MODFOLLOWING",
      "paymentBusinessCenters": ["USNY", "CLSA"],
      "paymentDateOffset": 0,
      "rollConvention": "5",
      "settlementCurrency": "USD",
      "settlementType": "CASH"
    },
    {
      "legId": "FLOATING-LEG-SOFR-LOOKBACK",
      "payerPartyReference": "ThisBank",
      "receiverPartyReference": "OurCounterparty",
      "notionalAmount": 50000000,
      "notionalCurrency": "USD",
      "rateType": "FLOATING",
      "floatingRateIndex": "USD-SOFR-COMPOUND",
      "spread": 0.0,
      "resetFrequency": "3M",
      "resetDayConvention": "PRECEDING",
      "resetBusinessCenters": ["USNY", "CLSA"],
      "resetDateOffset": -5,
      "paymentFrequency": "6M",
      "dayCountFraction": "ACT/360",
      "paymentDayConvention": "MODFOLLOWING",
      "paymentBusinessCenters": ["USNY", "CLSA"],
      "paymentDateOffset": 0,
      "rollConvention": "5",
      "settlementCurrency": "USD",
      "settlementType": "CASH"
    }
  ]
}